PietInterpreter/GUI.py
PietInterpreter/PietInterpreterCore.py
PietInterpreter/__init__.py
PietInterpreter/canvasManager.py
PietInterpreter/colors.py
PietInterpreter/dataStructures.py
PietInterpreter/errors.py
PietInterpreter/executeFunctions.py
PietInterpreter/helperFunctions.py
PietInterpreter/imageFunctions.py
PietInterpreter/infoManager.py
PietInterpreter/lexer.py
PietInterpreter/movementFunctions.py
PietInterpreter/tokenFunctions.py
PietInterpreter/tokens.py
pietinterpreter-1.0.10.dist-info/METADATA
pietinterpreter-1.0.10.dist-info/WHEEL
pietinterpreter-1.0.10.dist-info/entry_points.txt
pietinterpreter-1.0.10.dist-info/top_level.txt
pietinterpreter-1.0.10.dist-info/RECORD
