Metadata-Version: 2.4
Name: PietInterpreter
Version: 1.0.10
Summary: PietInterpreter is an interpreter for Piet-programs.
Home-page: https://github.com/anionDev/PietInterpreter
Author: Marius Göcke
Author-email: marius.goecke@gmail.com
Keywords: esoteric programming language
Classifier: Programming Language :: Python :: 3.10
Classifier: License :: OSI Approved :: MIT License
Classifier: Operating System :: POSIX :: Linux
Classifier: Operating System :: Microsoft :: Windows :: Windows 10
Classifier: Topic :: Terminals
Requires-Python: >=3.10
Requires-Dist: numpy>=2.3.2
Requires-Dist: Pillow>=11.3.0
Requires-Dist: pygubu>=0.38.2
Requires-Dist: ScriptCollection>=3.5.148
